{
	"confidants": {
		"lines":{
			"aeon":[
			[	["An acquaintance.", "A friend.", "This is Marie."], 
				["Do you DO want one.", "Can you even watch it in that room?", "What kind of show is that...?"],
				["Of course.", "You don't remember?"],
				["That must be rough.", "You're kidding me, right?", "You can't remember anything?"],
				["Did you live here before?", "Do you remember anything else?"]],
			[	["Play around.", "Peoplewatch.", "There's nothing to do."],
				["I don't mind.", "If you want to."],
				["I don't know.", "I think it's good.", "That's green, you know"],
				["I don't know.", "I think it's good.", "That's an eye-catching color."],
				["Of course.", "If you want to."],
				["There's meaning.", "You'll know once you have one."],
				["Let's hurry.", "You're not going?", "It'll sell out."]],
			[	["It's fun.", "It's pretty much my duty.", "I skip it sometimes."],
				["I'm showing her the school.", "Come with us."],
				["Of course.", "You spend youth with everyone."],
				["Let it go.", "Let's spend our youths.", "Wondering about your 'true self'?"]],
			[	["I see what you mean.", "Kanji isn't that old."],
				["It's not quite like that.", "That's about right."],
				["Sub-buttle.", "Subtle."],
				["I'll help.", "How?", "Good luck."]],
			[	["Are there any clues?", "I don't know.", "First, meditate."],
				["It's made of bamboo.", "Is it sold somewhere?"],
				["Tatsumi Textiles", "Marukyu Tofu", "Junes"],
				["It's not like that.", "We have business here.", "Of course it's a date."],
				["Can you?", "Anything will help."],
				["Do you remember something?", "Does your stomach hurt?"]],
			[	["She said it was old.", "She never saw anything like it."],
				["They're works of art.", "They're antiques."],
				["Old Man Daidara", "Old Lady Shiroku", "Aiya Owner"],
				["It's not like that.", "And you two?"],
				["At this store?", "We're doing some research."],
				["We want to learn about it.", "Do you know anything about it?"],
				["Are you all right?", "Don't strain yourself.", "Do you remember something?"],
				["Calm down.", "Let's try again.", "Take it easy."]],
			[	["Does your head hurt again?", "What about the comb?"],
				["Don't give up.", "Are you giving up?", "Coward."]],
			[	["You remember.", "I thought you forgot.", "That's a 'memory.'"],
				["I'll help.", "It's up to you.", "Don't forget 'em."],
				["Because I love you.", "Because you're my friend."]],
			[	["What's wrong?", "Bored?", "Don't snoop around."],
				["Leave it to me.", "Lots of memories won't do it."]],
			[	["I'm not hearing a 'Thank you.'", "It was fun."]]
			],
			"chariot":[
			[ ["Right.", "For what...?"],
			  ["I'm cool with it.", "I guess so...", "What a pain."]],
			[	["It's cute.", "It's very feminine.", "It's hilarious."]],
			[	["Exactly.", "None of your business.", "Quit bragging on her."],
				["Crack a joke.", "Badmouth Takeshi.", "Hold Chie's hand."]],
			[	["Wolfing it down, huh?", "Looks delicious.", "You look so happy."],
				["I'll look out for her.", "Yukiko isn't that weak.", "I worry more for you."]],
			[	["Exactly.", "It's eat or be eaten."],
				["Of course.", "Let the police handle it.", "What a pain..."]],
			[	["Hold Chier back", "Fight them yourself"],
				["It's no trouble.", "I'm used to it.", "Just think next time."]],
			[	["There's still time.", "That's the first step.", "It's hard to face yourself."]],
			[	["Let Chie do her thing", "Shield Chie", "Fight with Chie"],
				["It all turned out okay.", "You protected that kid.", "That was reckless."],
				["Will you be my girlfirned? (Romance)", "I'm counting on you. (Friendship)"]],
			[	["It was cleaner.", "It was messier.", "It was about the same."],
				["That sounds good.", "You're on your own."],
				["Hug her", "Do nothing"],
				["Don't worry about it.", "That's just like you."]],
			[	["Of course.", "Maybe not always."]]
			],
			"death": [
			[	["I just moved here.", "I won't be staying long."],
				["I think so, too.", "Everyone says so, but..."],
				["Death?", "What do you mean?"]],
			[	["Who are you talking about?", "So he didn't look like me?", "Stop staring at me."],
				["Yes, you do.", "No, you don't.", "This is stupid."]],
			[	["Of what?", "What about the river?"],
				["I'm jealous.", "What about now?"],
				["That's not true!", "Don't torture yourself."]]
			],
			"devil": [
			[	["What do you mean?", "I'm not interested.", "Please, by all means."]],
			[	["For the money.", "To be closer to you.", "To have something to do."],
				["I do.", "I do not.", "Right in front of me.", "Why do you ask?"],
				["Oh, yes.", "No...", "Stop it!"]],
			[	["Only part-time...", "I'm a high school student."],
				["What were you here for?",	"Why are you wearing black?", "We should meet again."]],
			[	["...Okay.", "I'd rather not know.", "...I can't stay in here."],
				["That's just how it is.", "It's good they get better.", "Why don't you switch jobs?"]],
			[	["What happened?", "It's like a soap opera."],
				["That can't be helped.", "I wish I'd seen it."],
				["Comfort her", "Cheer her up", "Ignore her"]],
			[	["Did something happen?", "Are you not feeling well?", "Are we done here?"],
				["Don't blame yourself.", "It couldn't be helped.", "Think about what you did."],
				["Watch her silently", "Say something to her"]],
			[	["You should get some rest...", "Hang in there."]],
			[	["Is there an emergency?", "At this time of night?"],
				["Overworking, I hear?", "It's important to rest."],
				["Physician, heal thyself.", "Can you help anyone now?", "Don't do it all yourself."],
				["Would 'he' want that?", "You're doing it for yourself.", "You're just running away."]],
			[	["Goodbye?", "Take care..."]]
			],
			"emperor": [
			[	["Apologize to her.", "You just need to change.", "That's what kids do."]],
			[	["Get ahold of yourself.", "Let's hurry.", "What happened?"],
				["That's good.", "I don't blame you.", "You wuss."],
				["Because of his hobbies?", "Because of his looks?", "Because of his attitude?"]],
			[	["Plenty.", "Nothing in particular...", "I forget."],
				["Violence isn't the answer.", "I'll go with you."],
				["Too bad you didn't find it.", "That was boring.", "You're giving him a new one?"]],
			[	["Just tell him the truth.", "This old man here made it."],
				["It was pretty amazing.", "Don't get cocky."]],
			[	["It's good for you.", "You're not happy?", "Looks like a pain..."]],
			[	["Don't call me 'bro.'", "Yeah, go ahead.", "I want to lern too."],
				["Your weak heart.", "Your past.", "I'm drawing a blank."]],
			[	["On what charges?", "Kanji didn't do anything.", "You got a warrant?"],
				["It's a misunderstanding.", "He was just being nice."],
				["Believe it!", "The truth is the truth.", "Tell him, Kanji."]],
			[	["Tell him?", "Why didn't you go before?", "How was it?"],
				["Good for you.", "Find more of them.", "Your 'own self'?"]]
			],
			"fortune": [
			[	["Really?", "I'm still worried about you.", "That's no fun."],
				["What happened?", "You don't need to go home?", "A thief in a sleuth's house?"],
				["You should be careful.", "Who would want your stuff?", "Remember that card...?"]],
			[	["A challenge for a duel?", "A love letter?", "That card business again...?"],
				["You won't read it?", "What if it's from a guy?", "What'll you do with it?"]],
			[	["Another love letter?", "Is it a guy this time?", "That 'card' again?"],
				["That's right.", "Why so uncomfortable?", "Running from a challenge?"],
				["Good luck.", "Let's catch him together"]],
			[	["Soak it.", "Burn it.", "Eat it."],
				["A riddle.", "A mailbox.", "A goat."],
				["What was it?", "Good, you got it back. (Understanding 5)"],
				["I guess I'll help.", "Let's do it.", "You're on your own."]],
			[	["Because I looked reliable.", "Because we looked 'close.'", "Because I looked useless."],
				["7 and 3 o'clock, maybe...?", "The phrasing is suspicious.", "The numbers are important."],
				["I'm glad you're a girl. (Romance Path)", "Your gender doesn't matter. (Friendship Path)", "Nothing you can do."]],
			[	["Maybe it's a math problem.", "Check the other cards again?", "Subtract '40' and '4'?"],
				["You'll still be you.", "People change.", "Don't be afraid."]],
			[	["You seem happy.", "Don't put yourself at risk.", "I feel kinda sad."],
				["Protect Naoto (Romance Path)", "Run with Naoto", "Fight back"]],
			[	["Somewhere bright.", "Somewhere high.", "Somewhere quiet."],
				["Cooking.", "Exercising.", "Throwing things away?"]],
			[	["Is it that interesting?", "Why don't you sit down?", "I can't relax..."],
				["Whatever you prefer.", "I like it higher."]],
			[	["It was a cinch.", "It was exciting.", "I was about to give up."],
				["Leave it to me!", "I want to be your partner.", "You're MY assistant."]]
			],
			"hanged": [
			[],
			[],
			[]
			],
			"hierophant": [
			[	["Hanging with friends.", "CLub meetings.", "Working.", "Nothing..."],
				["Do you still suspect me?", "Not good at talking?", "Tell me about yourself."],
				["That's stretching it.", "Should I call you big bro?"]],
			[	["Why not play with her?", "I feel sorry for her.", "Not good with kids?"],
				["Why?", "Fit or not, you're family.", "I don't get it."]],
			[	["Black.", "With cream.", "Cream and sugar.", "Surprise me."],
				["You don't have to do that.", "Thank you."]],
			[	["Looking for something?", "Can I help?", "Working at home?"],
				["Are you okay?", "What was that about?", "But Nanako..."]],
			[	["Let's not.", "Even if it's about family?", "Then let's go outside."],
				["You're right.", "Is this what she wants?", "That's just an excuse."]],
			[	["When's 'anytime'?", "This is more important, huh?"]],
			[	["Working at home again?", "Buying a new car?", "Want some coffee?"],
				["Because of Nanako.", "Because her killer's loose.", "Because you're a coward."]],
			[	["I don't mind.", "It was fun.", "Ask me next time."],
				["Was it hard?", "Do you regret now?", "You've stopped running?"]],
			[	["Thank you.", "What am I using now?", "My name? That's okay..."],
				["Go get 'em.", "Be careful.", "Leave it to me."]]
			],
			"jester": [
			[	["Why?", "You don't eat?"], 
				["She cares about you.", "That does sound annoying."]],
			[	["Why don't you come over for real?", "You shouldn't lie to her.", "I was a big ... kelp?"],
				["I'm a good cook.", "Nanako will be happy."],
				["What did you do instead?", "What kind of student were you?"],
				["Is having a job hard?", "You don't enjoy yourself now?"]],
			[	["Yeah, he does.", "Nope."],
				["That was a surprise.", "You like magic tricks?"]],
			[	["You're right.", "She won't learn anything that way.", "Is that how you do your job, too?"],
				["Nope, nothing.", "I don't want one."]],
			[	["You slacking off again?", "I'm busy enough, thanks."],
				["Good for you.", "Does it make you sad?", "What a miserable old woman."],
				["That's true.", "But doesn't it get lonely?"]]
			],
			"justice": [
			[	["What's wrong?", "Go ahead and ask."]],
			[	["I'll go buy some.", "Let's go buy some together.", "He'll live"],
				["I'm sorry.", "Hear her out.", "It's not Nanako's fault."]],
			[	["Why all these questions?", "Is there anything else?"],
				["They disappear.", "They go to heaven.", "I don't know."],
				["They have no choice.", "Because they enjoy it.", "I don't know."],
				["That's not true.", "He's protecting everyone.", "He's protecting you."]],
			[	["Related to you by blood.", "A person you love a lot.", "Always by your side."],
				["Did he say that?", "That's not true.", "You have me."],
				["Talk with her", "Put her to bed", "Listen to her talk"]],
			[	["Ask what happened", "Swear to it"],
				["He'll come.", "I don't know.", "I'll ask him with you."]],
			[	["Let's go look for her.", "Let's leave her alone."],
				["That's not true.", "Why?", "Okay."],
				["Why'd you come here?", "Let's go home.", "Your dad's worried."],
				["He hasn't forgotten.", "He won't abandon you.", "Don't worry."]],
			[	["I'll help you look for it.", "Nothing you can do now."],
				["He's lonely, too", "Because you're lonely."]],
			[	["I know.", "He loves you, too.", "What about me?"],
				["He still has you.", "She's not lost.", "I feel sorry for you, too."],
				["Talk to Nanako", "Put her to bed", "Play with her"]],
			[	["Sure thing.", "I think...", "I eat salad for breakfast!"],
				["Don't strain yourself.", "Let's do it.", "But I'm not your Mom..."]]
			],
			"lovers": [
			[	["Why?", "You don't eat out?", "Just order takeout."]],
			[	["You come here often?", "Can't you shop in Inaba...?", "What are you looking for?"]],
			[	["Yell", "Call the police", "Grab her hand and run"],
				["Go along with her.", "Deny it"],
				["I don't mind.", "Lying is wrong.", "It... It was a lie?"]],
			[	["All the time.", "Sometimes...", "Not really."],
				["That's right.", "No.", "I don't know..."]],
			[	["Give it to her yourself.", "Does she even need them?", "Why so interested in her?"],
				["That's not nice.", "He's worried about you.", "You're really quitting?"],
				["Having second thoughts?", "This was your decision.", "She'll understand."],
				["Sounds great.", "If you're serious...", "I can't decide that now."]],
			[	["She's cute, huh?", "Jealous?", "That's good, isn't it?"],
				["I'm happy.", "I'm miserable.", "That part doesn't matter."],
				["Cheer her up", "Move closer to her", "Laugh it off"]],
			[	["You mustn't cry!", "Cry all you want."],
				["Hold her (Romance)", "Stand there (Friendship)"]],
			[	["You regret leaving.", "You're selfish.", "'Risette' is Rise, too."]],
			[	["What do you mean?", "You want to see?", "I don't have any."]]
			],
			"magician": [
			[ ["It must be tough.", "You're bragging about it?", "Why are you infamous?"]],
			[	["He's sounding like you too.", "Teddie's cute.", "Hmm, you're looking hairier."],
				["You don't block them?", "Why not change addresses.", "Eh, what can you do?"]],
			[	["That must be hard.", "Dont' strain yourself.", "You're incredible."],
				["That's the spirit!", "Don't get too excited.", "What can you do...?"]],
			[	["Of course.", "Huh?", "What, don't you?"],
				["I have.", "I haven't.", "I will soon."]],
			[	["No problem.", "Tell me next time!", "It was fun."],
				["You're right.", "Man, you're mature.", "No need to hold back..."]],
			[	["Shut up!", "Calm down, man...", "I feel bad for Saki-senpai."],
				["You were just upset.", "Feel better now?", "I know how it is."]],
			[	["She dumped you?", "She died?"],
				["Just take it slow.", "I understand...", "Don't apologize."]],
			[	["Cheer up.", "Still sad about Saki-senpai?", "Be a man. Stand up straight."],
				["You're right.", "That's not true.", "I don't get it."]],
			[	["I didn't know.", "It can't be helped.", "'I guess'?"],
				["All right, but you hit me first.", "Then let's get equal!"]]
			],
			"moon": [
			[],
			[],
			[]
			],
			"priestess": [
			[	["Going to apply for one?", "Sensei?"],
				["Sounds good.", "What's that?", "You decide."]],
			[	["Making dinner at the inn?", "On an errand?"],
				["Good luck.", "There's no point.", "Any other skills?"],
				["Count me in!", "I don't mind.", "I dunno..."]],
			[	["Let's eat!", "My stomach's kinda...", "Did you taste it?"],
				["There's always next time.", "This won't cut it.", "Can I toss this?"],
				["It's okay.", "I'm having fun.", "Just don't feed me again."]],
			[	["What's all this for?", "Can you carry all that?"],
				["Sounds good to me.", "You said no?"],
				["Are you serious?", "That's selfish."]],
			[	["What are you making?", "Gotten any better yet?"],
				["Get someone to teach you.", "Keep practicing.", "Want me to teach you?"],
				["You're pretty bad.", "If you started a fire...", "They care about you."]],
			[	["You're not coming back?", "You're really leaving?"],
				["It's okay.", "They're not mistaken."]],
			[	["An interview?", "You're going to be on TV?"],
				["Yeah, you were.", "You were cool.", "You should've said more."]],
			[	["For everyone...", "For me...", "For you...", "It's a secret."],
				["You're my classmate. (No Romance)", "You're my friend. (No Romance)", "I really like you. (Romance)"]],
			[	["The futon good with you?", "The sofa good with you?", "The floor good with you?"],
				["That's good.", "Did you think it over?", "Good luck."],
				["Thank you.", "You'll protect me."]],
			[	["That's good.", "Did you think it over?", "Good luck."],
				["Thank you.", "Relying on the gods?"]]
			],
			"strength": [
			[	["Aiya.", "Junes.", "Let's go home."],
				["I'm jealous.", "Not happy about it?", "Sounds like a pain..."],
				["Sure.", "That's okay."]],
			[	["What do you mean?", "Just tell me how."],
				["That sucks.", "But it's just a sport...", "I can see that."],
				["Easier said than done...", "Leave it to me.", "What can I do?"]],
			[	["It's hard to imagine.", "I can see that."],
				["That's good for you.", "Cheer up, man.", "......"]],
			[	["It's been over for hours.", "You've got some nerve...", "Something wrong?"],
				["Get a grip, man.", "You just need a rest.", "Let's go do something fun."]],
			[	["You could say that...", "It's something else."],
				["You're right.", "A real game? Impossible...", "We gotta save Kou."],
				["You're quite a strategist.", "Isn't that blackmail...?", "What about yourself?"]],
			[	["You're thinking too much.", "Did they say anything?"],
				["What for?", "Planning to run away?"],
				["And once you know?", "You going to meet them?", "I'll go with you."]]
			],
			"sun": [
			[	["Effort is what matters.", "You do have talent. (Understanding 3)", "Maybe you should give up."],
				["Help out (+ Understanding)", "Watch (+ Diligence)"]],
			[	["You want me to help?", "Forget about it today."],
				["You don't want to go?", "They won't let you go?"],
				["That's a great attitude", "Is that what you want?"]],
			[	["Can you practice at home?", "Can it wait until tomorrow?", "Why don't you give up? (Courage 3)"],
				["Outside?", "Want me to help out? (+ Understanding, Understanding 3)", "Alright, follow me! (+ Expression, Courage 3)"],
				["Yep.", "No you're not. (Understanding 3)", "Just hang in there. (+ Diligence)"]],
			[	["Talk to her.", "Leave her alone."],
				["Don't worry, you can do it! (+ Expression)", "But who else is there? (+ Courage)", "It's okay to mess up. (Understanding 3)"],
				["What do you mean?", "You take that back?"]],
			[	["Stick up for Ayane (+ Expression)", "Keep quiet"],
				["Comfort her (+ Expression)", "Pat her on the head", "Hold her"]],
			[	["Reveal your feelings for her (Romance)", "Change the subject (Friendship)"]],
			[	["Wanna grab some food?", "Wanna go out and have fun?", "Wanna come to my house? (Courage 5)"]]
			],
			"temperance": [
			[	["Yeah, I like kids.", "I'm on the fence.", "I hate kids."],
				["Do you like him?", "You have problems with him?"]],
			[	["Probably.", "I don't know."],
				["Do you love Yuuta?", "Do you love your husband?"]],
			[]
			],
			"tower": [
			[	["Of course.", "I don't know.", "I don't think so."], 
				["Sure I do.", "No, what?"],
				["Wait until next time.", "I'll stay and help you. (Diligence 5)"]],
			[	["It's fun.", "It's strict.", "It's boring."],
				["I'm a transfer student, too.", "Well, it is the countryside.", "Make friends with him."]],
			[	["That's just how it is.", "That's not true."],
				["It's the law.", "You don't have to go.", "You're not the only one. (+ Courage)"]],
			[	["Yes, there is.", "No, there isn't.", "Not that I know of..."],
				["Just ignore them.", "Put some effort into it.", "Leave it to me."],
				["It's not like you.", "I don't mind. (+ Understanding)"]],
			[	["Were they a pain in the ass?", "Didn't you join in?"],
				["You're just at that age.", "That's not true."],
				["Of course.", "That's just one reason.", "That's not it."]],
			[	["Work hard, and you can be.", "You already are one.", "Just give up now."],
				["The other day at school... (+ Expression)", "About these murders... / The other day on TV, I saw... (+ Expression)", "What I like in a girl is... (+ Courage)"]],
			[	["I do.", "Nope.", "This guy."],
				["You must be tired.", "You must be possessed."],
				["Ask what he's worried about", "Cheer him up", "Leave him alone"]]
			]},
		"stats": {
				"aeon":
				[
					[	[0, 0, 0], [0, 0, 0], [0, 0], [0, 0, 0], [0, 0]],
					[	[2, 2, 2], [0, 0], [0, 0, 0], [0, 0, 0], [0, 0], [0, 0], [3, 3, 0]],
					[	[3, 3, 0], [0, 0], [0, 0], [0, 0, 0]],
					[	[0, 0], [0, 0], [0, 0], [0, 0, 0]],
					[	[0, 0, 0], [3, 3], [0, 0, 0], [0, 0, 0], [0, 0], [0, 0]],
					[	[0, 0], [3, 3], [0, 0, 0], [0, 0], [0, 0], [0, 0], [0, 0, 0], [0, 0, 0]],
					[	[0, 0], [0, 0, 0]],
					[	[0, 0, 0], [3, 3, 3], [0, 0]],
					[	[3, 3, 3], [3, 3]],
					[	[0, 3]]
				],
				"chariot": 
				[
					[	[3, 0]],
					[	[3, 3, 2]],
					[	[0, 2, 3], [3, 3, 2]],
					[	[3, 3, 3], [3, 3, 3]],
					[	[0, 3], [3, 0, 0]],
					[	[0, 0], [3, 0, 0]],
					[	[3, 3, 3]],
					[	[0, 0, 0], [3, 3, 0], [0, 0]],
					[	[0, 3, 3], [0, 3], [0, 0], [0, 0]],
					[	[0, 0]]
				],
				"death": 
				[
					[	[0, 0], [0, 0], [0, 0]],
					[	[0, 0, 0], [0, 0, 0]],
					[	[0, 0], [0, 0], [0, 0]]
				],
				"devil": 
				[
					[ [2, 2, 0]],
					[ [3, 2, 2], [2, 0, 2, 0], [0, 2, 3]],
					[	[0, 0], [0, 0, 0], [2, 2, 2], [0, 0, 0]],
					[	[0, 2], [0, 0], [3, 2, 0]],
					[	[0, 0, 0], [0, 0, 0], [0, 0]],
					[	[2, 3]],
					[	[0, 0], [0, 0], [0, 0, 0], [0, 0, 0]],
					[	[0, 0]]
				],
				"emperor": 
				[
					[	[3, 3, 2]],
					[	[0, 0, 0], [0, 0, 0]],
					[	[3, 2, 0], [3, 3], [0, 0, 3]],
					[	[0, 0], [3, 2]],
					[	[0, 0, 0]],
					[	[3, 3, 3], [0, 0, 0]],
					[	[0, 3, 3], [0, 0], [3, 2, 3]],
					[	[2, 3, 3], [3, 3, 0]]
				],
				"fortune": 
				[
					[	[0, 3, 0], [0, 0, 0], [3, 0, 3]],
					[	[3, 0, 3], [0, 0, 0]],
					[	[0, 0, 3], [0, 0, 0], [3, 3]],
					[	[0, 3, 0], [0, 3, 0], [0, 3], [2, 3, -2]],
					[	[3, 3, 3], [0, 0, 3], [0, 3, 0]],
					[	[0, 0, 3], [0, 0, 3]],
					[	[3, 2, 3], [0, 0, 0]],
					[	[0, 3, 0], [0, 0, 3]],
					[	[0, 3, 0], [0, 0]],
					[	[3, 3, 3], [3, 3, 3]]
				],
				"hanged": 
				[],
				"hierophant": 
				[
					[	[2, 0, 3, 0], [0, 2, 3], [3, 3]],
					[	[0, 0, 0], [0, 3, 3]],
					[	[3, 3, 3, 3], [3, 2]],
					[	[0, 3, 2], [3, 2, 3]],
					[	[2, 2, 3], [0, 0, 0]],
					[	[0, 2], [0, 0, 0]],
					[	[0, 0, 3], [2, 2, 3]],
					[	[2, 3, 2], [3, 2, 3]],
					[	[3, 2, 3], [3, 3, 3]]
				],
				"jester":
				[	
					[	[0, 0], [0, 0], [0, 3]],
					[	[2, 0, 0], [3, 2], [0, 0], [0, 0]],
					[	[0, 2], [3, 2]],
					[	[3, 0, 0], [0, 0], [0, 0]],
					[	[0, 0], [0, 0, 0], [3, 0]]
				],
				"justice": 
				[
					[ [3, 2], [3, 0] ],
					[	[3, 3, 0], [0, 0, 3]],
					[	[0, 3], [0, 3, 2], [0, 0, 2], [0, 0, 2]],
					[	[0, 3, 0], [3, 0, 2], [2, 0, 3]],
					[	[0, 2], [3, 0, 3]],
					[	[2, 0], [0, 0, 0], [0, 3, 0], [0, 0, 0]],
					[	[3, 0], [3, 3]],
					[	[3, 3, 0], [3, 3, 3], [3, 0, 3]],
					[	[3, 2, 0], [2, 3, 0]]
				],
				"lovers": 
				[
					[	[2, 3, 3]],
					[	[3, 3, 3]],
					[	[0, 3, 3], [3, 0], [3, 0, 3]],
					[	[3, 3, 2], [0, 3, 3]],
					[	[0, 0, 0], [0, 0, 0], [3, 0, 3], [3, 3, 0]],
					[	[0, 0, 0], [2, 0, 3], [3, 3, 3]],
					[	[0, 0], [0, 0]],
					[	[3, 3, 3]],
					[	[0, 0, 0]]
				],
				"magician": 
				[ 
					[ [3, 0, 0]],
					[	[0, 2, 3], [0, 0, 0]],
					[	[1, 2, 3], [2, 0, 0]],
					[	[3, 3, 0], [0, 0, 3]],
					[	[3, 3, 3], [3, 3, 0]],
					[	[0, 0, 0], [3, 3, 3]],
					[	[0, 0], [0, 0, 0]],
					[	[2, 0, 0], [3, 3, 3]],
					[	[0, 0, 0], [0, 0]]
				],
				"moon": 
				[],
				"priestess": 
				[
					[	[3, 2], [3, 2, 0]],
					[	[3, 2], [3, 0, 0], [3, 2, 0]],
					[	[3, 2, 2], [3, 0, 0], [2, 3, 2]],
					[	[3, 0], [0, 0], [0, 0]],
					[	[0, 2], [0, 2, 0], [0, 0, 3]],
					[	[0, 0], [3, 3]],
					[	[0, 0], [0, 3, 3]],
					[	[3, 2, 3, 0], [0, 0, 0]],
					[	[0, 0, 0], [0, 0, 0], [3, 3]],
					[	[0, 0, 0], [0, 0]]
				],
				"strength":
				[
					[	[3, 3, 2], [2, 0, 0], [2, 2]],
					[	[3, 0], [0, 3, 2], [0, 3, 2]],
					[	[2, 2], [2, 2, 0]],
					[	[0, 3, 2], [0, 2, 3]],
					[	[0, 0], [3, 2, 2], [3, 3, 3]],
					[	[0, 0], [0, 0], [0, 0, 0]]
				],
				"sun": 
				[
					[ [3, 2, 0], [3, 2]],
					[ [2, 3], [0, 0], [2, 0]],
					[	[0, 0, 3], [0, 3, 3], [0, 3, 2]],
					[	[0, 0], [2, 0, 3]],
					[	[0, 0], [0, 0, 3]],
					[	[0, 0]],
					[	[3, 3, 3]]
				],
				"temperance": 
				[
					[	[0, 2, 3], [0, 0]],
					[	[2, 2], [0, 0]]
				],
				"tower": 
				[
					[	[0, 0, 0], [2, 0], [0, 2]],
					[	[0, 2, 3], [0, 3, 0]],
					[	[2, 0], [0, 0, 3]],
					[	[0, 2, 0], [0, 3, 0], [2, 2]],
					[	[0, 0], [0, 0], [0, 2, 3]],
					[	[0, 0, 0], [0, 2, 3]],
					[	[0, 0, 3], [0, 0], [2, 3, 0]]
				]},
		"ranks": {
				"aeon": [2, 3, 4, 5, 6, 7, 8, 9, "Romance", "Friendship"],
				"chariot": [2, 3, 4, 5, 6, 7, 8, 9, "Romance", "Friendship"],
				"death": [2, 3],
				"devil": [2, 3, 4, 5, 6, 7, 9],
				"emperor": [2, 3, 4, 5, 6, 7, 8, 9],
				"fortune": [2, 3, 4, 5, 6, 7, 8, 9, "Romance", "Friendship"],
				"hanged": [],
				"hierophant": [2, 3, 4, 5, 6, 7, 8, 9, "MAX"],
				"jester": [2, 3, 4, 5, 6],
				"justice": [2, 3, 4, 5, 6, 7, 8, 9, "MAX"],
				"lovers": [2, 3, 4, 5, 6, 7, 8, 9, "Romance"],
				"magician": [2, 3, 4, 5, 6, 7, 8, 9, "MAX"],
				"moon": [],
				"priestess": [2, 3, 4, 5, 6, 7, 8, 9, "Romance", "Friendship"],
				"strength": [2, 3, 4, 5, 6, 7],
				"sun": [2, 3, 4, 5, 7, 8, "9 Romance"],
				"temperance": [2, 3],
				"tower": [2, 3, 4, 5, 6, 7, 8]},
		"requirements": {
				"aeon": [0, 0, 0, "Later than 07/24", 0, 0, 0, 0, 0, 0], 
				"chariot": [0, 0, 0, 0, 0, 0, 0, 0, 0],
				"death": [0, 0],
				"devil": ["Later than 05/25", 0, 0, 0, 0, 0, 0, 0, 0],
				"emperor": [0, 0, 0, 0, 0, 0, 0, 0],
				"fortune": ["Later than 10/21", 0, 0, 0, 0, 0, 0, 0, 0, 0],
				"hanged": ["Later than 07/08 \n Requires Rank 3 Understanding"],
				"hierophant": ["Rank 2 Expression", 0, "Rank 3 Expression", "Rank 4 Expression", 0, 0, 0, 0],
				"jester": [0, 0, 0, 0, 0],
				"justice": [0, 0, "Rank 3 Expression", 0, "Rank 5 Expression", 0, 0, 0, 0],
				"lovers": [0, 0, 0, 0, 0, 0, 0, 0],
				"magician": [0, 0, 0, 0, 0, 0, 0, 0, 0],
				"moon": [],
				"priestess": [0, 0, 0, 0, 0, 0, 0, 0, 0, 0],
				"strength": [0, 0, 0, 0, 0, 0],
				"sun": [0, 0, 0, 0, 0, 0],
				"temperance": [0, 0],
				"tower": ["Later than 05/25 \n Requires Rank 5 Understanding", 0, 0, 0, 0, 0, 0]}
	},
	"exams": {
		"class_questions": {
			"04/14": ["What is the year before 1 AD called?"],
			"04/18": ["The word ”alphabet” comes from the words ”alpha” and what other one?"],
			"04/20": ["How many parts are there in Murakami's ”The Wind-Up Bird Chronicle”?"],
			"04/23": ["Hey! Mr. Hanamura, wake up! What was the first economic bubble incident in the world?"],
			"04/25": ["Answer this one: what's it called, when you gain more muscle after getting sore through exercise?"],
			"04/26": ["Well, Miss Satonaka. Tell me which of these don't exist."],
			"04/30": ["What is the greatest canyon in the solar system?"],
			"05/07": ["Do you know how Soseki Natsume translated the English phrase ”I love you” into Japanese."],
			"05/26": ["Tell me how the theory that the pyramids were built by slaves was disproven?"],
			"06/08": ["What sport is ”heikin-dai”?"],
			"06/13": ["Tell me what kind of exercise builds up lactic acid in the muscles!"],
			"06/15": ["Morals are about virtue! Morale is ... Tell me, Hanamura! You seem to be lacking in morals!"],
			"06/20": ["What period did Japan first implement bonus pay?"],
			"06/27": ["Answer this: What is identity?"],
			"06/30": ["Which one of these is the name of a real river?"],
			"07/04": ["Who said this: ”Man is but a reed, the most feeble thing in nature; but he is a thinking reed”?"],
			"07/07": ["What is the beginning of ”Gakumon no Susume” a reference to?"],
			"07/13": ["What is the medical term for brainfreeze?"],
			"07/14": ["Which famous Heian-era monk famously used a wrong version of the ”応” kanfji?"],
			"07/15": ["Which line can a typhoon never cross?"],
			"07/16": ["Tell me what makes the king of hearts look different from the other kings in a standard deck fo cards."],
			"09/01": ["”Venison” is the meat of what animal?"],
			"09/05": ["Which of the following is a kigo for fall?"],
			"09/17": ["How short was history's shortest war?"],
			"09/20": ["What do yo ucall somebody who's between ninety and one hundred years old?"],
			"09/28": ["While we're on the subject of apple, what part of the human body has an apple in it? Anybody know?"],
			"10/04": ["Which of these sports also uses an anchor?"],
			"10/05": ["Where would you find Japan on Japan on a map made in a foreign country?"],
			"10/08": ["Be brave! Tell me what bird's name means ”coward” in English!"],
			"10/11": ["What did Napoleon have invented?"],
			"10/12": ["Do you know what vegetablew as used to make the first jack-o'-lanterns?"],
			"10/13": ["What kind of fish was I just talking about?"],
			"11/01": ["Tell me what the ”figure” in ”figure skating” refers to!"],
			"11/04": ["Jmm... Who can tell me what kind of bird a kanko-dori is. You, Hana-chan! You look like you have no problem with silence!"],
			"11/07": ["Which country do you think the South Pole belongs to?"],
			"11/11": ["What desert is the Welwitscha found in?"],
			"11/17": ["Hey, wait... What was the question? Is that even in the textbook? The boots of ”bridal”? What...?"],
			"11/22": ["Do you know what an ”atlas” is?"],
			"11/24": ["0, 1, 1, 2, 3, 5, 8, 13... What is this sequence called?"],
			"11/25": ["There are over 130 ancient pyramids in Egypt, but do you know who's buried in the biggest one?"],
			"11/26": ["Which of these is considered a ”rice cake”?"],
			"01/10": ["Tell me, what are you supposed to put on top of a kagami mochi?"],
			"01/14": ["”Toso” is a traditional drink for the new year, but what does that name mean?"],
			"01/19": ["In the Vietnamese zodiac, which animal is used in the place of the rabbit?"],
			"01/25": ["What color is the snow that falls in Europe in spring?"],
			"01/30": ["What's the next unit of measurement up from a terabyte?"],
			"02/01": ["What color were the pyramids originally."]
		},
		"class_answers": {
			"04/14": ["0 AD.", "1 BC.", "-1 AD."],
			"04/18": ["Better.", "Bet.", "Beta."],
			"04/20": ["Two", "Three", "Seven"],
			"04/23": ["The South Sea Bubble", "The Mississippi Company", "The Great Depression", "Tulip mania"],
			"04/25": ["Overgrowth.", "Overcompensation.", "Overexertion."],
			"04/26": ["Amicable numbers", "Betrothed numbers", "Marriage numbers", "Sociable numbers"],
			"04/30": ["Kurobe Canyon.", "Valles Marineris.", "Grand Canyon."],
			"05/07": ["I love you.", "I could die.", "I love thee.", "The moon is beautiful, isn't it?"],
			"05/26": ["Resumes.", "Contracts.", "Attendance logs.", "Employee ID cards."],
			"06/08": ["Balance Beam.", "High Dive.", "Uneven Bars.", "Synchronized Dancing."],
			"06/13": ["Anaerobics.", "Aerobics.", "Oxyrobics."],
			"06/15": ["A reward.", "The desire to grow.", "Cheerfulness in a group.", "Gambling spirit."],
			"06/20": ["Edo.", "Meiji.", "Taisho."],
			"06/27": ["Uniqueness.", "Difference.", "Individuality."],
			"06/30": ["Lame Duck River.", "Pis Pis River.", "Mahony's Phony River."],
			"07/04": ["Pascal.", "Descartes.", "Nietzsche."],
			"07/07": ["The Bible.", "The Japanese constitution.", "The U.S. Declaration of Independence."],
			"07/13": ["Intercranial hypothermitis.", "Neurocapillary constriction.", "Sphenopalatine ganglioneuralgia.", "Trigeminal nociception."],
			"07/14": ["Kuukai.", "Saicho.", "Genshin."],
			"07/15": ["The equator.", "The International Date Line.", "The Prime Meridian."],
			"07/16": ["He has no mustache.", "He has an axe.", "His mouth is open.", "He's looking to the right."],
			"09/01": ["Wild boar.", "Deer.", "Moose.", "All of the above."],
			"09/05": ["Brisk.", "Rain.", "Peaceful.", "Sunset."],
			"09/17": ["40 minutes.", "40 hours.", "40 days."],
			"09/20": ["A deciprecentenarian.", "A ninetygenarian.", "A nonagenarian."],
			"09/28": ["Ankles.", "Kness.", "Throat.", "Temple."],
			"10/04": ["Tug-of-war.", "Swimming.", "Wrestling.", "Shot put."],
			"10/05": ["The left edge.", "The right edge.", "It's not even on the map."],
			"10/08": ["Dove.", "Sparrow.", "Chicken.", "Crow."],
			"10/11": ["Cans.", "Glass jars.", "Dictionaries.", "Brandy."],
			"10/12": ["Turnips.", "Watermelons.", "Eggplants.", "I really think it was pumpkins."],
			"10/13": ["Ojisan.", "Obasan.", "Oniisan."],
			"11/01": ["Geometric shapes.", "The human body.", "Arithmatic computation."],
			"11/04": ["A cuckoo.", "An eagle.", "A sparrow.", "A crow."],
			"11/07": ["Japan.", "Australia.", "England.", "No country."],
			"11/11": ["Nubian.", "Sahara.", "Namib.", "Kalahari."],
			"11/17": ["Bride wine", "Bride sake", "Bride ale"],
			"11/22": ["A compass.", "A globe.", "A book of maps."],
			"11/24": ["The Fibonacci sequence.", "The Farey sequence.", "The Sequence of differences."],
			"11/25": ["Giza.", "Khufu.", "Tutenkhamen.", "Cleopatra."],
			"11/26": ["Dango.", "A bale of rice.", "Senbei.", "Mochi."],
			"01/10": ["An orange.", "A coin.", "An incense stick."],
			"01/14": ["Appease the demons.", "Bury the demons.", "Fuse the demons."],
			"01/19": ["Elephant.", "Bear.", "Cat."],
			"01/25": ["Red", "Green", "Black"],
			"01/30": ["Femtobyte.", "Trilobyte.", "Petabyte."],
			"02/01": ["Gold.", "White.", "Black."]
		},
		"key": [
			[1, 2, 1, 3, 1, 2, 1, 3, [1, 2], [2, 0], [3, 3], 2, 0, 0, 2, 1, 2, 1, 0, 2, 2, 0, 0, 0, [2, 0], 
			[0, 1], [2, 0], [2, 2], 3, 0, 0, 2, 2, 0, 2, 1, 0, 0, [2, 1], [0, 3], [0, 2], [2, 1], [2, 0], 
			 0, 0, 3, 2, 2, 2, 0, 1, 3, [1, 0], [1, 1], [0, 0], [3, 0], [2, 3], 0, 1, 2, 0, 2, 2, 1, [1, 0], [3, 2], [1, 0], [1, 1]]
		],
		"exam_questions": {
			"05/09": ["What is it called when muscles grow after exercise?", "What is the year before 1 A.D. called?"],
			"05/10": ["Which kind of these types of numbers does not exist?", "Who translated ”I love you” as ”The moon is beautiful, isn't it?”"],
			"05/11": ["Who said, ”As soon as laws are necessary for men, they are no longer fit for freedom”?", "Which of the following is the highest mountain in the solar system?"],
			"07/19": ["What is morale?", "What sport is ”heikin-dai”?"],
			"07/20": ["It is said, ”Even Kobo made mistakes in writing.” Which kanji did he make a mistake on?", "In which period did Japan first implement bonus pay?"],
			"07/21": ["Which king in a deck of cards is missing a mustache?", "Who said this: ”Man is but a reed, the most feeble thing in nature; but he is a thinking reed”?"],
			"07/22": ["Which one of these is the name of a real river?", "What is the beginning of ”Gakumon no Susume” a reference to?"],
			"10/14": ["What part of the body contains the ”Adam's apple”?", "Where would you find Japan on a map made in a foreign country?"],
			"10/15": ["How short was history's shortest war?", "”Venison” is the meat of what animal?"],
			"10/17": ["What is the Japanese name for ”panda”?", "Which bird is falsely known for being cowardly in the English phrase ”to stikc one's head in the sand”?"],
			"10/18": ["What was the name of the Wasan textbook that came out in the Edo period?", "What did Napoleon have invented?"],
			"10/19": ["Which season is the adjective ”brisk” a kigo for?", "What is ”Dragon's Blood”?"],
			"11/26": ["What does French food stem from.", "What does the ”figure” in ”figure skating” refer to?"],
			"11/29": ["Who is buried in the biggest pyramid in Egypt?", "What is a book of maps called?"],
			"11/28": ["What does French food stem from.", "What does the ”figure” in ”figure skating”"],
			"11/30": ["What word has the words ”bride ale” as its roots?", "What kind of bird is a ”kanko-dori”?"],
			"12/01": ["Which country does the South Pole belong to?", "0, 1, 1, 2, 3, 5, 8, 13... What is this sequence called?"],
			"12/02": ["What desert is the Welwitscha found in?", "Which of these is considered a ”rice cake”?"],
			"02/06": ["The word ”alphabet” comes from the words ”alpha” and what other one?", "How was the theory that the pyramids were built by slaves disproven?"],
			"02/07": ["What drink name means ”bury demons”?", "What is the medical term for brainfreeze?"],
			"02/08": ["What is the Japanese zodiac equivalent to the ”cat” in the Vietnamese zodiac?", "What vegetable was used to make the first jack-o'-lanterns?"],
			"02/09": ["What color were the pyramics when they were first built?", "What gets mixed with snow in Europe that sometiems causes it to turn red?"]
		},
		"exam_answers": {
			"05/09": [["Overgrowth.", "Overcompensation.", "Overexertion."], ["0 B.C.", "0 A.D.", "1 B.C."]],
			"05/10": [["Amicable numbers", "Betrothed numbers", "Marriage numbers", "Sociable numbers"], ["Soseki Natsume", "Shimei Futabatei", "Yukichi Fukuzawa"]],
			"05/11": [["Sartre", "Nietzsche", "Pascal", "Pythagoras"], ["Mt. Everest.", "Gula Mons.", "Maxwell Montes.", "Olympus Mons."]],
			"07/19": [["A reward.", "The desire to grow.", "Cheerfulness in a group.", "Gambling spirit."], ["Balance Beam.", "High Dive.", "Uneven Bars.", "Synchronized Dancing"]],
			"07/20": [["応", "夫", "門"], ["Edo.", "Meiji.", "Taisho."]],
			"07/21": [["King of clubs.", "King of diamonds.", "King of hearts.", "King of spades."], ["Pascal.", "Descartes.", "Nietzsche."]],
			"07/22": [["Lame Duck River.", "Mahony's Phony River.", "Pis Pis River."], ["The Bible.", "The Japanese constitution.", "The U.S. Declaration of Independence."]],
			"10/14": [["Ankles.", "Knees.", "Throat.", "Temple."], ["The left edge.", "The right edge.", "It's not even on the map."]],
			"10/15": [["40 minutes.", "40 hours.", "40 days."], ["Wild boar.", "Deer.", "Moose.", "All of the above."]],
			"10/17": [["Black and white bears.", "Monochrome bears.", "Tabby bears."], ["Chicken.", "Sparrow.", "Ostrich.", "Crow."]],
			"10/18": [["Wasan shojo.", "Nerdette.", "Math Girl."], ["Cans.", "Glass jars.", "Dictionaries.", "Brandy."]],
			"10/19": [["Spring.", "Summer.", "Fall.", "Winter."], ["Plant resin.", "Animal saliva.", "Blood of a dragon."]],
			"11/28": [["Spanish food.", "Italian food.", "Japanese food."], ["Geometric shapes.", "The human body.", "Arithmatic computation."]],
			"11/29": [["Giza", "Khufu", "Tutenkhamen", "Cleopatra"], ["Index", "Atlas", "Bookmark"]],
			"11/30": [["Bridal.", "Bridle.", "Bridge."], ["A cuckoo.", "An eagle.", "A sparrow.", "A crow."]],
			"12/01": [["Japan.", "Australia.", "England.", "No country."], ["The Fibonacci sequence.", "The Farey sequence.", "The Sequence of differences."]],
			"12/02": [["Nubian.", "Sahara.", "Namib.", "Kalahari."], ["Dango.", "A bale of rice.", "Senbei.", "Mochi."]],
			"02/06": [["Better.", "Beta.", "Bet."], ["Attendance logs.", "Contracts.", "Employee ID cards.", "Resumes."]],
			"02/07": [["Toshi.", "Uchi.", "Soto.", "Toso."], ["Intercranial hypothermitis.", "Neurocapillary constriction.", "Sphenopalatine ganglioneuralgia.", "Trigeminal nociception."]],
			"02/08": [["Elephant.", "Rabbit.", "Tiger.", "Mouse."], ["Turnips.", "Watermelons.", "Eggplants."]],
			"02/09": [["Gold.", "White.", "Black."], ["Human blood.", "The Sahara Desert sand.", "Red dye."]]
		},
	"dates": ["04/14", "04/18", "04/20", "04/23", "04/25", "04/26", "04/30", "05/07", "05/09", "05/10", "05/11", "05/26", "06/08", "06/13", "06/15", 
	 "06/20", "06/27", "06/30", "07/04", "07/07", "07/13", "07/14", "07/15", "07/16", "07/19", "07/20", "07/21", "07/22", "09/01", "09/05", "09/17", 
	 "09/20", "09/28", "10/04", "10/05", "10/08", "10/11", "10/12", "10/14", "10/15", "10/17", "10/18", "10/19", "11/01", "11/04", "11/07", "11/11", 
	 "11/17", "11/22", "11/24", "11/25", "11/26", "11/28", "11/29", "11/30", "12/01", "12/02", "01/10", "01/14", "01/19", "01/25", "01/30", "02/01", 
	 "02/06", "02/07", "02/08", "02/09"],
	"exam_names": {
	"05/09":"First Trimester Midterms", 
	"07/19":"First Trimester Finals", 
	"10/14":"Second Trimester Midterms", 
	"11/28":"Second Trimester Finals",
	"02/06":"Third Trimester Finals"}},
	"cooking": [	
		[	["Meat Stew", ["Simmer without a lid", "Use strong heat", "Simmer with a drop lid"]],
			["Ginger Pork", ["Drenching it in oil", "Scoring it with a knife", "Blanching it"]],
			["Sweet and Sour Pork", ["Use potato starch", "Use flour", "Simmer with vinegar"]],
			["Yakiniku Bento", ["Use sugar instead", "Use soy sauce instead", "Use vinegar instead"]],
			["Potato salad", ["Mix with mayonnaise and cool", "Stir fry with ham", "Smash them while still  hot"]],
			["Hamburgers", ["Look for the bubbles on top", "Poke the center and feel it", "Cut a hole and look for juice"]],

			[2, 1, 0, 1, 2, 2]]
	],
	"names": [
	["aeon", "chariot", "death", "devil", "emperor", "empress", "fortune", "hanged", 
		"hermit", "hierophant", "jester", "justice", "lovers", "moon", "priestess", "star", "sun", "temperance", "tower"], 
	["[AEON]", "wagen", "tod", "teufel", "herrscher", "herrscherin", "fortuna", "gehängter",
		"eremit", "hierophant", "[JESTER]", "justiz", "liebhaber", "mond", "hohepriesterin", "stern", "sonne", "mäßigkeit", "turm"]
		]
}